deisa/core/__init__.py
deisa/core/__version__.py
deisa/core/interface.py
deisa/core/py.typed
deisa/core/validator.py
deisa_core-0.2.0.dist-info/licenses/LICENSE
deisa_core-0.2.0.dist-info/METADATA
deisa_core-0.2.0.dist-info/WHEEL
deisa_core-0.2.0.dist-info/top_level.txt
deisa_core-0.2.0.dist-info/RECORD
