Metadata-Version: 2.4
Name: deisa-core
Version: 0.2.0
Summary: Core Deisa tools and utilities.
Home-page: https://github.com/deisa-project/deisa-core
Author: Benoît Martin
Author-email: bmartin@cea.fr
License: MIT
Project-URL: Bug Reports, https://github.com/deisa-project/deisa-core/issues
Project-URL: Source, https://github.com/deisa-project/deisa-core
Keywords: deisa
Classifier: Programming Language :: Python :: 3.8
Classifier: Operating System :: OS Independent
Classifier: Development Status :: 3 - Alpha
Requires-Python: >=3.8
License-File: LICENSE
Requires-Dist: dask
Requires-Dist: numpy
Provides-Extra: test
Requires-Dist: pytest; extra == "test"
Requires-Dist: dask; extra == "test"
Requires-Dist: distributed; extra == "test"
Requires-Dist: numpy; extra == "test"
Dynamic: author
Dynamic: author-email
Dynamic: classifier
Dynamic: description
Dynamic: description-content-type
Dynamic: home-page
Dynamic: keywords
Dynamic: license
Dynamic: license-file
Dynamic: project-url
Dynamic: provides-extra
Dynamic: requires-dist
Dynamic: requires-python
Dynamic: summary
